setup.py
dwight.egg-info/PKG-INFO
dwight.egg-info/SOURCES.txt
dwight.egg-info/dependency_links.txt
dwight.egg-info/requires.txt
dwight.egg-info/top_level.txt
src/dwight/__init__.py
src/dwight/dwight.py
src/scripts/dwight