Metadata-Version: 1.0
Name: dwight
Version: 0.8.0
Summary: Run Django management commands against arbitrary settings files.
Home-page: http://github.com/fish2000/dwight/
Author: Alexander Böhn
Author-email: fish2000@gmail.com
License: GPLv2
Download-URL: http://github.com/fish2000/dwight/zipball/master
Keywords: django management command execute run settings
Platform: any
Classifier: Development Status :: 5 - Production/Stable
Classifier: License :: OSI Approved :: GNU General Public License (GPL)
Classifier: Operating System :: MacOS
Classifier: Operating System :: Microsoft :: Windows
Classifier: Operating System :: OS Independent
Classifier: Operating System :: POSIX
Classifier: Operating System :: Unix
Classifier: Programming Language :: Python :: 2.6
